{
	"meta": {
		"deploymentTarget": {
			"branch": "",
			"name": "Wire",
			"version": {
				"major": 7,
				"minor": 22,
				"patch": 3
			}
		},
		"saveTarget": {
			"branch": "",
			"name": "Wire",
			"version": {
				"major": 7,
				"minor": 22,
				"patch": 3
			}
		}
	},
	"preset": {
		"Pastel Pokedots": {
			"101": {
				"type": "float",
				"value": 0.08045999705791473
			},
			"103": {
				"type": "color",
				"value": [
					0.22745096683502197,
					0.24313725531101227,
					0.67843139171600342,
					1
				]
			},
			"107": {
				"type": "color",
				"value": [
					0,
					1,
					0.53725481033325195,
					1
				]
			},
			"120": {
				"type": "bool",
				"value": true
			},
			"176": {
				"type": "float",
				"value": 2.41379308700561523
			},
			"39": {
				"type": "float",
				"value": 0.90804600715637207
			},
			"61": {
				"type": "float",
				"value": -0.03448300063610077
			},
			"62": {
				"type": "float",
				"value": -0.14942499995231628
			},
			"70": {
				"type": "float",
				"value": 70.1149444580078125
			},
			"76": {
				"type": "float",
				"value": 0.31034499406814575
			},
			"84": {
				"type": "integer",
				"value": 12
			},
			"85": {
				"type": "float",
				"value": 0.31034499406814575
			},
			"90": {
				"type": "integer",
				"value": 0
			},
			"95": {
				"type": "float",
				"value": -0.1264369934797287
			}
		}
	}
}